{
  "generated_at": "2026-07-16T20:38:42.323889+00:00",
  "results": [
    {
      "source": "dexscreener-boosted",
      "symbol": "BULD",
      "name": "BULD",
      "address": "2AEuuDipca4mbqhQDS473GgeX8vA5S7d9voTm8hepump",
      "price_usd": "0.000004001",
      "market_cap_usd": 4001,
      "liquidity_usd": 6071.88,
      "volume_24h_usd": 8020838.64,
      "price_change_24h_pct": -89.43,
      "created_age_hours": 15.401657689344619,
      "url": "https://dexscreener.com/solana/9seuhjuk18dxcohfxkvdptkw5sx7cbuoxhs6djrdf8gk",
      "raw": {
        "chainId": "solana",
        "dexId": "pumpswap",
        "url": "https://dexscreener.com/solana/9seuhjuk18dxcohfxkvdptkw5sx7cbuoxhs6djrdf8gk",
        "pairAddress": "9sEuhjUK18dXcoHFxKvDpTkW5sx7CBUoxHs6djRdF8gK",
        "baseToken": {
          "address": "2AEuuDipca4mbqhQDS473GgeX8vA5S7d9voTm8hepump",
          "name": "BULD",
          "symbol": "BULD"
        },
        "quoteToken": {
          "address": "So11111111111111111111111111111111111111112",
          "name": "Wrapped SOL",
          "symbol": "SOL"
        },
        "priceNative": "0.00000005276",
        "priceUsd": "0.000004001",
        "txns": {
          "m5": {
            "buys": 0,
            "sells": 0
          },
          "h1": {
            "buys": 14,
            "sells": 3
          },
          "h6": {
            "buys": 26,
            "sells": 60
          },
          "h24": {
            "buys": 29857,
            "sells": 26656
          }
        },
        "volume": {
          "h24": 8020838.64,
          "h6": 478.22,
          "h1": 47.28,
          "m5": 0
        },
        "priceChange": {
          "h1": 0.97,
          "h6": -9.93,
          "h24": -89.43
        },
        "liquidity": {
          "usd": 6071.88,
          "base": 758337047,
          "quote": 40.05806
        },
        "fdv": 4001,
        "marketCap": 4001,
        "pairCreatedAt": 1784178859000,
        "info": {
          "imageUrl": "https://cdn.dexscreener.com/cms/images/-gGKfmhXGVX2rtHe?width=800&height=800&quality=95&format=auto",
          "header": "https://cdn.dexscreener.com/cms/images/NcmPHUVXXJBjxQuF?width=1500&height=500&quality=95&format=auto",
          "openGraph": "https://cdn.dexscreener.com/token-images/og/solana/2AEuuDipca4mbqhQDS473GgeX8vA5S7d9voTm8hepump?timestamp=1784234400000",
          "websites": [
            {
              "url": "https://buld.live",
              "label": "Website"
            }
          ],
          "socials": [
            {
              "url": "https://x.com/BULD_MEME",
              "type": "twitter"
            },
            {
              "url": "https://t.me/BULD_SOLANA",
              "type": "telegram"
            },
            {
              "url": "https://discord.gg/QpHnScPDd",
              "type": "discord"
            }
          ]
        },
        "boosts": {
          "active": 50
        }
      },
      "score": 897.121,
      "risk_score": 1,
      "risk_score_raw": 1,
      "risk_label": null,
      "risks_detail": [],
      "mint_authority_renounced": true,
      "freeze_authority_renounced": true,
      "lp_locked_pct": 100,
      "holder_count": 1193,
      "top10_holder_pct": 92.8
    },
    {
      "source": "dexscreener-boosted",
      "symbol": "BARRON",
      "name": "The Insider",
      "address": "GqQc4tjs6RkZt1EdsehKLZvNDTpZc9n3UHGxnbfNpump",
      "price_usd": "0.0001328",
      "market_cap_usd": 132830,
      "liquidity_usd": 32294.79,
      "volume_24h_usd": 3486239.52,
      "price_change_24h_pct": 317,
      "created_age_hours": 23.188720463528103,
      "url": "https://dexscreener.com/solana/cu5ovy5cnci62cacpz5lvjm6dfrheqrssurzwfrdqgqc",
      "raw": {
        "chainId": "solana",
        "dexId": "pumpswap",
        "url": "https://dexscreener.com/solana/cu5ovy5cnci62cacpz5lvjm6dfrheqrssurzwfrdqgqc",
        "pairAddress": "CU5oVY5cNCi62CACpz5LVJm6dFrHEQrssuRzwFrDQgqc",
        "baseToken": {
          "address": "GqQc4tjs6RkZt1EdsehKLZvNDTpZc9n3UHGxnbfNpump",
          "name": "The Insider",
          "symbol": "BARRON"
        },
        "quoteToken": {
          "address": "So11111111111111111111111111111111111111112",
          "name": "Wrapped SOL",
          "symbol": "SOL"
        },
        "priceNative": "0.000001750",
        "priceUsd": "0.0001328",
        "txns": {
          "m5": {
            "buys": 28,
            "sells": 20
          },
          "h1": {
            "buys": 303,
            "sells": 306
          },
          "h6": {
            "buys": 4019,
            "sells": 3432
          },
          "h24": {
            "buys": 41811,
            "sells": 34697
          }
        },
        "volume": {
          "h24": 3486239.52,
          "h6": 306212.76,
          "h1": 16707.12,
          "m5": 800.36
        },
        "priceChange": {
          "m5": -4.97,
          "h1": -11.19,
          "h6": -50.11,
          "h24": 317
        },
        "liquidity": {
          "usd": 32294.79,
          "base": 121296039,
          "quote": 213.2949
        },
        "fdv": 132830,
        "marketCap": 132830,
        "pairCreatedAt": 1784150825000,
        "info": {
          "imageUrl": "https://cdn.dexscreener.com/cms/images/k7oopzq4rHQ9mXRN?width=800&height=800&quality=95&format=auto",
          "header": "https://cdn.dexscreener.com/cms/images/wwJl43RW3DFq0O_W?width=1500&height=500&quality=95&format=auto",
          "openGraph": "https://cdn.dexscreener.com/token-images/og/solana/GqQc4tjs6RkZt1EdsehKLZvNDTpZc9n3UHGxnbfNpump?timestamp=1784234400000",
          "websites": [
            {
              "url": "https://x.com/i/communities/2038242738966331737",
              "label": "Website"
            }
          ],
          "socials": [
            {
              "url": "https://x.com/BarronTrumpSOLA",
              "type": "twitter"
            }
          ]
        },
        "boosts": {
          "active": 100
        }
      },
      "score": 55.8,
      "risk_score": 1,
      "risk_score_raw": 1,
      "risk_label": null,
      "risks_detail": [],
      "mint_authority_renounced": true,
      "freeze_authority_renounced": true,
      "lp_locked_pct": 100,
      "holder_count": 3795,
      "top10_holder_pct": 26.7
    },
    {
      "source": "dexscreener-boosted",
      "symbol": "HOMIE",
      "name": "Welcome Back Homie",
      "address": "E7vTVLLaxV3y68cpnDx2Q7ExeznhWgJKwPziKDsrpump",
      "price_usd": "0.0004522",
      "market_cap_usd": 452287,
      "liquidity_usd": 55707.79,
      "volume_24h_usd": 3474513.93,
      "price_change_24h_pct": 1213,
      "created_age_hours": 15.301230067206488,
      "url": "https://dexscreener.com/solana/5fg5azit5ed8paz12vdtttmgxw5monsutyxjwa2w6qdy",
      "raw": {
        "chainId": "solana",
        "dexId": "pumpswap",
        "url": "https://dexscreener.com/solana/5fg5azit5ed8paz12vdtttmgxw5monsutyxjwa2w6qdy",
        "pairAddress": "5fg5azit5ed8PaZ12vdtTTMGXw5moNsutYXJWA2w6qDY",
        "baseToken": {
          "address": "E7vTVLLaxV3y68cpnDx2Q7ExeznhWgJKwPziKDsrpump",
          "name": "Welcome Back Homie",
          "symbol": "HOMIE"
        },
        "quoteToken": {
          "address": "So11111111111111111111111111111111111111112",
          "name": "Wrapped SOL",
          "symbol": "SOL"
        },
        "priceNative": "0.000005962",
        "priceUsd": "0.0004522",
        "txns": {
          "m5": {
            "buys": 62,
            "sells": 100
          },
          "h1": {
            "buys": 875,
            "sells": 1535
          },
          "h6": {
            "buys": 6365,
            "sells": 10272
          },
          "h24": {
            "buys": 23940,
            "sells": 29658
          }
        },
        "volume": {
          "h24": 3474513.93,
          "h6": 1002933.71,
          "h1": 134993.93,
          "m5": 8497.57
        },
        "priceChange": {
          "m5": 1.83,
          "h1": 14.09,
          "h6": -16.39,
          "h24": 1213
        },
        "liquidity": {
          "usd": 55707.79,
          "base": 61408369,
          "quote": 368.2246
        },
        "fdv": 452287,
        "marketCap": 452287,
        "pairCreatedAt": 1784179220000,
        "info": {
          "imageUrl": "https://cdn.dexscreener.com/cms/images/6P3zP_VAKSZT6rSh?width=800&height=800&quality=95&format=auto",
          "header": "https://cdn.dexscreener.com/cms/images/w00bdGkgI7biQYz1?width=1500&height=500&quality=95&format=auto",
          "openGraph": "https://cdn.dexscreener.com/token-images/og/solana/E7vTVLLaxV3y68cpnDx2Q7ExeznhWgJKwPziKDsrpump?timestamp=1784234400000",
          "websites": [
            {
              "url": "https://backhomie.lol/",
              "label": "Website"
            }
          ],
          "socials": [
            {
              "url": "https://x.com/welcome_homie",
              "type": "twitter"
            }
          ]
        },
        "boosts": {
          "active": 100
        }
      },
      "score": 42.488,
      "risk_score": 1,
      "risk_score_raw": 1,
      "risk_label": null,
      "risks_detail": [],
      "mint_authority_renounced": true,
      "freeze_authority_renounced": true,
      "lp_locked_pct": 100,
      "holder_count": 2331,
      "top10_holder_pct": 21.9
    },
    {
      "source": "dexscreener-boosted",
      "symbol": "CASHGOAT",
      "name": "Cash Goat",
      "address": "AWJkSP77HTYnWyWiBfRoK5nurwP4ApVw1YeEugmepump",
      "price_usd": "0.0001015",
      "market_cap_usd": 101593,
      "liquidity_usd": 25866.78,
      "volume_24h_usd": 1455196.92,
      "price_change_24h_pct": 171,
      "created_age_hours": 17.1009719535319,
      "url": "https://dexscreener.com/solana/b2rgfp2rtcobx5witgdgfuby1xevpwmxqpxqmawqrru8",
      "raw": {
        "chainId": "solana",
        "dexId": "pumpswap",
        "url": "https://dexscreener.com/solana/b2rgfp2rtcobx5witgdgfuby1xevpwmxqpxqmawqrru8",
        "pairAddress": "B2RGFp2RTcobX5witgdGFUby1xeVpwmXQpXqmawqRru8",
        "baseToken": {
          "address": "AWJkSP77HTYnWyWiBfRoK5nurwP4ApVw1YeEugmepump",
          "name": "Cash Goat",
          "symbol": "CASHGOAT"
        },
        "quoteToken": {
          "address": "So11111111111111111111111111111111111111112",
          "name": "Wrapped SOL",
          "symbol": "SOL"
        },
        "priceNative": "0.000001339",
        "priceUsd": "0.0001015",
        "txns": {
          "m5": {
            "buys": 0,
            "sells": 0
          },
          "h1": {
            "buys": 40,
            "sells": 32
          },
          "h6": {
            "buys": 394,
            "sells": 318
          },
          "h24": {
            "buys": 14212,
            "sells": 15713
          }
        },
        "volume": {
          "h24": 1455196.92,
          "h6": 31072.82,
          "h1": 4204.76,
          "m5": 0
        },
        "priceChange": {
          "h1": -9.62,
          "h6": 16.95,
          "h24": 171
        },
        "liquidity": {
          "usd": 25866.78,
          "base": 126719697,
          "quote": 171.3196
        },
        "fdv": 101593,
        "marketCap": 101593,
        "pairCreatedAt": 1784172741000,
        "info": {
          "imageUrl": "https://cdn.dexscreener.com/cms/images/N252x-eoPmB8BH0p?width=800&height=800&quality=95&format=auto",
          "header": "https://cdn.dexscreener.com/cms/images/lYNv9TM81lIFpR65?width=1500&height=500&quality=95&format=auto",
          "openGraph": "https://cdn.dexscreener.com/token-images/og/solana/AWJkSP77HTYnWyWiBfRoK5nurwP4ApVw1YeEugmepump?timestamp=1784234400000",
          "websites": [
            {
              "url": "https://cashgoat.fun/",
              "label": "Website"
            }
          ],
          "socials": [
            {
              "url": "https://x.com/the_cashgoat",
              "type": "twitter"
            },
            {
              "url": "https://t.me/the_cashgoat",
              "type": "telegram"
            }
          ]
        },
        "boosts": {
          "active": 100
        }
      },
      "score": 36.215,
      "risk_score": 1,
      "risk_score_raw": 1,
      "risk_label": null,
      "risks_detail": [],
      "mint_authority_renounced": true,
      "freeze_authority_renounced": true,
      "lp_locked_pct": 100,
      "holder_count": 1709,
      "top10_holder_pct": 31.4
    },
    {
      "source": "dexscreener-boosted",
      "symbol": "PROPHECY",
      "name": "The Prophecy",
      "address": "5yJgw6a8bb1nRsmEBr6vzX5pt6sQekzqG9nfmxqMpump",
      "price_usd": "0.00004123",
      "market_cap_usd": 41239,
      "liquidity_usd": 16081.96,
      "volume_24h_usd": 774967.92,
      "price_change_24h_pct": 31.48,
      "created_age_hours": 12.076292111409506,
      "url": "https://dexscreener.com/solana/3y4tnmjfekutardg9jhhqucmexprt1wwtkzu5zx1n46b",
      "raw": {
        "chainId": "solana",
        "dexId": "pumpswap",
        "url": "https://dexscreener.com/solana/3y4tnmjfekutardg9jhhqucmexprt1wwtkzu5zx1n46b",
        "pairAddress": "3y4tnmjFEKUTaRdG9jhhQUCMExpRT1wWTKzu5ZX1n46B",
        "baseToken": {
          "address": "5yJgw6a8bb1nRsmEBr6vzX5pt6sQekzqG9nfmxqMpump",
          "name": "The Prophecy",
          "symbol": "PROPHECY"
        },
        "quoteToken": {
          "address": "So11111111111111111111111111111111111111112",
          "name": "Wrapped SOL",
          "symbol": "SOL"
        },
        "priceNative": "0.0000005436",
        "priceUsd": "0.00004123",
        "txns": {
          "m5": {
            "buys": 15,
            "sells": 12
          },
          "h1": {
            "buys": 149,
            "sells": 171
          },
          "h6": {
            "buys": 1136,
            "sells": 1278
          },
          "h24": {
            "buys": 10134,
            "sells": 8309
          }
        },
        "volume": {
          "h24": 774967.92,
          "h6": 106529.86,
          "h1": 14670.29,
          "m5": 1511.02
        },
        "priceChange": {
          "m5": -2.62,
          "h1": -31.93,
          "h6": -29.54,
          "h24": 31.48
        },
        "liquidity": {
          "usd": 16081.96,
          "base": 194909417,
          "quote": 106.03892
        },
        "fdv": 41239,
        "marketCap": 41239,
        "pairCreatedAt": 1784190830000,
        "info": {
          "imageUrl": "https://cdn.dexscreener.com/cms/images/eHEglf7VYDXiVIl3?width=800&height=800&quality=95&format=auto",
          "header": "https://cdn.dexscreener.com/cms/images/JeatBqIvK3JghUob?width=1500&height=500&quality=95&format=auto",
          "openGraph": "https://cdn.dexscreener.com/token-images/og/solana/5yJgw6a8bb1nRsmEBr6vzX5pt6sQekzqG9nfmxqMpump?timestamp=1784234400000",
          "websites": [],
          "socials": [
            {
              "url": "https://x.com/i/communities/1993670548581421113",
              "type": "twitter"
            }
          ]
        },
        "boosts": {
          "active": 100
        }
      },
      "score": 36.065,
      "risk_score": 1,
      "risk_score_raw": 1,
      "risk_label": null,
      "risks_detail": [],
      "mint_authority_renounced": true,
      "freeze_authority_renounced": true,
      "lp_locked_pct": 100,
      "holder_count": 986,
      "top10_holder_pct": 39.0
    },
    {
      "source": "dexscreener-boosted",
      "symbol": "CASHBULL",
      "name": "CASHBULL",
      "address": "3YudidgEnPyMekuUCDEUf79MPqce8FHWF4ZSBV64pump",
      "price_usd": "0.000006391",
      "market_cap_usd": 6391,
      "liquidity_usd": 5953.55,
      "volume_24h_usd": 205845.52,
      "price_change_24h_pct": -79.88,
      "created_age_hours": 3.7556552758110895,
      "url": "https://dexscreener.com/solana/5zwncts7cxkdp5cem6mstowrbgjpgttbpc1qn8bye5w5",
      "raw": {
        "chainId": "solana",
        "dexId": "pumpswap",
        "url": "https://dexscreener.com/solana/5zwncts7cxkdp5cem6mstowrbgjpgttbpc1qn8bye5w5",
        "pairAddress": "5zwnCTs7CXKDp5Cem6mStowRBGjpgTTbPC1qn8byE5W5",
        "baseToken": {
          "address": "3YudidgEnPyMekuUCDEUf79MPqce8FHWF4ZSBV64pump",
          "name": "CASHBULL",
          "symbol": "CASHBULL"
        },
        "quoteToken": {
          "address": "So11111111111111111111111111111111111111112",
          "name": "Wrapped SOL",
          "symbol": "SOL"
        },
        "priceNative": "0.00000008427",
        "priceUsd": "0.000006391",
        "txns": {
          "m5": {
            "buys": 12,
            "sells": 7
          },
          "h1": {
            "buys": 2332,
            "sells": 1327
          },
          "h6": {
            "buys": 5152,
            "sells": 3569
          },
          "h24": {
            "buys": 5152,
            "sells": 3569
          }
        },
        "volume": {
          "h24": 205845.52,
          "h6": 205845.52,
          "h1": 23842.36,
          "m5": 331.68
        },
        "priceChange": {
          "m5": -7.26,
          "h1": -89.71,
          "h6": -79.88,
          "h24": -79.88
        },
        "liquidity": {
          "usd": 5953.55,
          "base": 465758728,
          "quote": 39.2493
        },
        "fdv": 6391,
        "marketCap": 6391,
        "pairCreatedAt": 1784220784000,
        "info": {
          "imageUrl": "https://cdn.dexscreener.com/cms/images/oo-3Iwk-KWNuwMeU?width=800&height=800&quality=95&format=auto",
          "header": "https://cdn.dexscreener.com/cms/images/IRnB7jAUXKVytBv4?width=1500&height=500&quality=95&format=auto",
          "openGraph": "https://cdn.dexscreener.com/token-images/og/solana/3YudidgEnPyMekuUCDEUf79MPqce8FHWF4ZSBV64pump?timestamp=1784234400000",
          "websites": [
            {
              "url": "https://www.cashbull.shop/",
              "label": "Website"
            }
          ],
          "socials": [
            {
              "url": "https://x.com/cashbullsol",
              "type": "twitter"
            }
          ]
        },
        "boosts": {
          "active": 500
        }
      },
      "score": 31.87,
      "risk_score": 3,
      "risk_score_raw": 25,
      "risk_label": "warn",
      "risks_detail": [
        "Low Liquidity"
      ],
      "mint_authority_renounced": true,
      "freeze_authority_renounced": true,
      "lp_locked_pct": 100,
      "holder_count": 358,
      "top10_holder_pct": 75.2
    },
    {
      "source": "dexscreener-boosted",
      "symbol": "BeastBull",
      "name": "The Beast of Skypiea",
      "address": "G1K4L2nWmwz9s4k31adUKvMaRRYyf9jrkvsrtc7spump",
      "price_usd": "0.0002165",
      "market_cap_usd": 216567,
      "liquidity_usd": 35668.33,
      "volume_24h_usd": 768421.35,
      "price_change_24h_pct": 222,
      "created_age_hours": 2.8755561330837676,
      "url": "https://dexscreener.com/solana/eggckcpfct4tttep1bshvxypgc848rxfgsanhc9gep4u",
      "raw": {
        "chainId": "solana",
        "dexId": "pumpswap",
        "url": "https://dexscreener.com/solana/eggckcpfct4tttep1bshvxypgc848rxfgsanhc9gep4u",
        "pairAddress": "EggcKcPFCT4ttTeP1bsHvXYPgC848RXFGsanhC9GeP4u",
        "baseToken": {
          "address": "G1K4L2nWmwz9s4k31adUKvMaRRYyf9jrkvsrtc7spump",
          "name": "The Beast of Skypiea",
          "symbol": "BeastBull"
        },
        "quoteToken": {
          "address": "So11111111111111111111111111111111111111112",
          "name": "Wrapped SOL",
          "symbol": "SOL"
        },
        "priceNative": "0.000002854",
        "priceUsd": "0.0002165",
        "txns": {
          "m5": {
            "buys": 329,
            "sells": 38
          },
          "h1": {
            "buys": 3953,
            "sells": 741
          },
          "h6": {
            "buys": 13147,
            "sells": 2571
          },
          "h24": {
            "buys": 13147,
            "sells": 2571
          }
        },
        "volume": {
          "h24": 768421.35,
          "h6": 768421.35,
          "h1": 169021.38,
          "m5": 8453.65
        },
        "priceChange": {
          "m5": -0.07,
          "h1": 8.02,
          "h6": 222,
          "h24": 222
        },
        "liquidity": {
          "usd": 35668.33,
          "base": 82416574,
          "quote": 234.9019
        },
        "fdv": 216567,
        "marketCap": 216567,
        "pairCreatedAt": 1784223953000,
        "info": {
          "imageUrl": "https://cdn.dexscreener.com/cms/images/fGf5gvLgHT6XaeAE?width=800&height=800&quality=95&format=auto",
          "header": "https://cdn.dexscreener.com/cms/images/4hjepcvT4cvq6Q_e?width=1500&height=500&quality=95&format=auto",
          "openGraph": "https://cdn.dexscreener.com/token-images/og/solana/G1K4L2nWmwz9s4k31adUKvMaRRYyf9jrkvsrtc7spump?timestamp=1784234400000",
          "websites": [
            {
              "url": "https://beastbull.vip/",
              "label": "Website"
            }
          ],
          "socials": [
            {
              "url": "https://x.com/BeastBullSol",
              "type": "twitter"
            }
          ]
        },
        "boosts": {
          "active": 50
        }
      },
      "score": 20.253,
      "risk_score": 1,
      "risk_score_raw": 1,
      "risk_label": null,
      "risks_detail": [],
      "mint_authority_renounced": true,
      "freeze_authority_renounced": true,
      "lp_locked_pct": 100,
      "holder_count": 5461,
      "top10_holder_pct": 12.1
    },
    {
      "source": "dexscreener-boosted",
      "symbol": "CUBEMAN",
      "name": "CUBEMAN",
      "address": "HVRtNeFPrDcAA9Yu3WrTEdCsTLGJiYDiQbqjg3efpump",
      "price_usd": "0.0007552",
      "market_cap_usd": 755256,
      "liquidity_usd": 67411.41,
      "volume_24h_usd": 1640464.25,
      "price_change_24h_pct": 2217,
      "created_age_hours": 15.507629196641709,
      "url": "https://dexscreener.com/solana/4z3zkjiksbxgr7pvkfsjbuk2gmkhmttfaghmgwpago8d",
      "raw": {
        "chainId": "solana",
        "dexId": "pumpswap",
        "url": "https://dexscreener.com/solana/4z3zkjiksbxgr7pvkfsjbuk2gmkhmttfaghmgwpago8d",
        "pairAddress": "4z3ZkJiksBXGr7PVkfSJBuK2GmkHmTTfaGHmGWPAgo8D",
        "baseToken": {
          "address": "HVRtNeFPrDcAA9Yu3WrTEdCsTLGJiYDiQbqjg3efpump",
          "name": "CUBEMAN",
          "symbol": "CUBEMAN"
        },
        "quoteToken": {
          "address": "So11111111111111111111111111111111111111112",
          "name": "Wrapped SOL",
          "symbol": "SOL"
        },
        "priceNative": "0.000009957",
        "priceUsd": "0.0007552",
        "txns": {
          "m5": {
            "buys": 38,
            "sells": 20
          },
          "h1": {
            "buys": 647,
            "sells": 350
          },
          "h6": {
            "buys": 4151,
            "sells": 2328
          },
          "h24": {
            "buys": 25807,
            "sells": 15954
          }
        },
        "volume": {
          "h24": 1640464.25,
          "h6": 484437.88,
          "h1": 80388.93,
          "m5": 4582.14
        },
        "priceChange": {
          "m5": -4.99,
          "h1": -8.31,
          "h6": 34.45,
          "h24": 2217
        },
        "liquidity": {
          "usd": 67411.41,
          "base": 44641258,
          "quote": 444.2412
        },
        "fdv": 755256,
        "marketCap": 755256,
        "pairCreatedAt": 1784178477000,
        "info": {
          "imageUrl": "https://cdn.dexscreener.com/cms/images/w7KWj2VQkAqs-y1z?width=800&height=800&quality=95&format=auto",
          "header": "https://cdn.dexscreener.com/cms/images/PAWh6sJZUJb5ldJW?width=1500&height=500&quality=95&format=auto",
          "openGraph": "https://cdn.dexscreener.com/token-images/og/solana/HVRtNeFPrDcAA9Yu3WrTEdCsTLGJiYDiQbqjg3efpump?timestamp=1784234400000",
          "websites": [
            {
              "url": "https://cubeman.lol/",
              "label": "Website"
            },
            {
              "url": "https://pump.fun/coin/HVRtNeFPrDcAA9Yu3WrTEdCsTLGJiYDiQbqjg3efpump",
              "label": "Live Cubeman"
            }
          ],
          "socials": [
            {
              "url": "https://x.com/the_cubeman",
              "type": "twitter"
            }
          ]
        },
        "boosts": {
          "active": 100
        }
      },
      "score": 16.473,
      "risk_score": 1,
      "risk_score_raw": 1,
      "risk_label": null,
      "risks_detail": [],
      "mint_authority_renounced": true,
      "freeze_authority_renounced": true,
      "lp_locked_pct": 100,
      "holder_count": 3658,
      "top10_holder_pct": 22.6
    },
    {
      "source": "dexscreener-boosted",
      "symbol": "DBULL",
      "name": "Delusional Bull",
      "address": "DiaXHsNJwvGXEjx1HN7phGL7YfHPtBuvzHoCk28Apump",
      "price_usd": "0.00003805",
      "market_cap_usd": 38057,
      "liquidity_usd": 14666.93,
      "volume_24h_usd": 257244.26,
      "price_change_24h_pct": 20.13,
      "created_age_hours": 7.457144724663629,
      "url": "https://dexscreener.com/solana/5wifkqwqhhzrtssvgcqfnxqpcrdw4ft7gcmdygkhwqjw",
      "raw": {
        "chainId": "solana",
        "dexId": "pumpswap",
        "url": "https://dexscreener.com/solana/5wifkqwqhhzrtssvgcqfnxqpcrdw4ft7gcmdygkhwqjw",
        "pairAddress": "5WiFKQWqhHzrTsSvGcQfnxQpCrDw4fT7gcmdYGKHwQjW",
        "baseToken": {
          "address": "DiaXHsNJwvGXEjx1HN7phGL7YfHPtBuvzHoCk28Apump",
          "name": "Delusional Bull",
          "symbol": "DBULL"
        },
        "quoteToken": {
          "address": "So11111111111111111111111111111111111111112",
          "name": "Wrapped SOL",
          "symbol": "SOL"
        },
        "priceNative": "0.0000005015",
        "priceUsd": "0.00003805",
        "txns": {
          "m5": {
            "buys": 8,
            "sells": 19
          },
          "h1": {
            "buys": 228,
            "sells": 269
          },
          "h6": {
            "buys": 1526,
            "sells": 1571
          },
          "h24": {
            "buys": 3375,
            "sells": 3119
          }
        },
        "volume": {
          "h24": 257244.26,
          "h6": 111223.93,
          "h1": 21448.89,
          "m5": 461.68
        },
        "priceChange": {
          "m5": -2.64,
          "h1": -7.07,
          "h6": -37.14,
          "h24": 20.13
        },
        "liquidity": {
          "usd": 14666.93,
          "base": 191556336,
          "quote": 97.2178
        },
        "fdv": 38057,
        "marketCap": 38057,
        "pairCreatedAt": 1784207459000,
        "info": {
          "imageUrl": "https://cdn.dexscreener.com/cms/images/RtQqqL0mFYI9BSdN?width=800&height=800&quality=95&format=auto",
          "header": "https://cdn.dexscreener.com/cms/images/Q3VPIBxiqszS-Ik0?width=1500&height=500&quality=95&format=auto",
          "openGraph": "https://cdn.dexscreener.com/token-images/og/solana/DiaXHsNJwvGXEjx1HN7phGL7YfHPtBuvzHoCk28Apump?timestamp=1784234400000",
          "websites": [
            {
              "url": "https://delusionalbull.fun/",
              "label": "Website"
            }
          ],
          "socials": [
            {
              "url": "https://x.com/dbullonsol?s=11",
              "type": "twitter"
            },
            {
              "url": "https://t.me/DBULL_PORTAL",
              "type": "telegram"
            }
          ]
        },
        "boosts": {
          "active": 100
        }
      },
      "score": 14.814,
      "risk_score": 1,
      "risk_score_raw": 1,
      "risk_label": null,
      "risks_detail": [],
      "mint_authority_renounced": true,
      "freeze_authority_renounced": true,
      "lp_locked_pct": 100,
      "holder_count": 603,
      "top10_holder_pct": 43.8
    },
    {
      "source": "dexscreener-boosted",
      "symbol": "bul",
      "name": "smol bull",
      "address": "DRhgZun6hRwH9ZuN8WnBqNg2o3SxGrPXdXh51XXfpump",
      "price_usd": "0.0001281",
      "market_cap_usd": 128197,
      "liquidity_usd": 27379.74,
      "volume_24h_usd": 529367.68,
      "price_change_24h_pct": 301,
      "created_age_hours": 19.607670182156035,
      "url": "https://dexscreener.com/solana/37hxlluia8ztgzhdemyabrnevv94thut44hc6rtvh2xn",
      "raw": {
        "chainId": "solana",
        "dexId": "pumpswap",
        "url": "https://dexscreener.com/solana/37hxlluia8ztgzhdemyabrnevv94thut44hc6rtvh2xn",
        "pairAddress": "37HXLLUiA8ZtgzhdEMyaBrneVv94tHUt44hC6RTVH2Xn",
        "baseToken": {
          "address": "DRhgZun6hRwH9ZuN8WnBqNg2o3SxGrPXdXh51XXfpump",
          "name": "smol bull",
          "symbol": "bul"
        },
        "quoteToken": {
          "address": "So11111111111111111111111111111111111111112",
          "name": "Wrapped SOL",
          "symbol": "SOL"
        },
        "priceNative": "0.000001689",
        "priceUsd": "0.0001281",
        "txns": {
          "m5": {
            "buys": 32,
            "sells": 19
          },
          "h1": {
            "buys": 2059,
            "sells": 275
          },
          "h6": {
            "buys": 4146,
            "sells": 1901
          },
          "h24": {
            "buys": 13645,
            "sells": 5597
          }
        },
        "volume": {
          "h24": 529367.68,
          "h6": 146028.51,
          "h1": 20792.94,
          "m5": 2023.13
        },
        "priceChange": {
          "m5": -7.66,
          "h1": -24.96,
          "h6": 38.17,
          "h24": 301
        },
        "liquidity": {
          "usd": 27379.74,
          "base": 106324404,
          "quote": 181.2219
        },
        "fdv": 128197,
        "marketCap": 128197,
        "pairCreatedAt": 1784163717000,
        "info": {
          "imageUrl": "https://cdn.dexscreener.com/cms/images/zPed_U4lEZ0uu7Rx?width=800&height=800&quality=95&format=auto",
          "header": "https://cdn.dexscreener.com/cms/images/FCYK5_TWZTB76IoK?width=1500&height=500&quality=95&format=auto",
          "openGraph": "https://cdn.dexscreener.com/token-images/og/solana/DRhgZun6hRwH9ZuN8WnBqNg2o3SxGrPXdXh51XXfpump?timestamp=1784234400000",
          "websites": [
            {
              "url": "https://Smol-bull.fun",
              "label": "Website"
            }
          ],
          "socials": [
            {
              "url": "https://x.com/bulonsol_",
              "type": "twitter"
            },
            {
              "url": "https://t.me/smolbullportal",
              "type": "telegram"
            }
          ]
        },
        "boosts": {
          "active": 100
        }
      },
      "score": 11.436,
      "risk_score": 1,
      "risk_score_raw": 1,
      "risk_label": null,
      "risks_detail": [],
      "mint_authority_renounced": true,
      "freeze_authority_renounced": true,
      "lp_locked_pct": 100,
      "holder_count": 8852,
      "top10_holder_pct": 25.3
    },
    {
      "source": "dexscreener-boosted",
      "symbol": "CHOCOLATE",
      "name": "Yummy ",
      "address": "8weM5kskjcg5A8SpfSkJGPVhL9RpJ7Lsu1Hs8ghSpump",
      "price_usd": "0.0001188",
      "market_cap_usd": 118823,
      "liquidity_usd": 25671.29,
      "volume_24h_usd": 128451.53,
      "price_change_24h_pct": 39.44,
      "created_age_hours": 32.73994176791721,
      "url": "https://dexscreener.com/solana/cuxztwfbcayctfhogsxcj2nkdzmj9psn1s9zutv6ivp4",
      "raw": {
        "chainId": "solana",
        "dexId": "pumpswap",
        "url": "https://dexscreener.com/solana/cuxztwfbcayctfhogsxcj2nkdzmj9psn1s9zutv6ivp4",
        "pairAddress": "CUxZtWfBCaYCtFHogSxcj2nkdzmj9psn1s9zuTv6iVP4",
        "baseToken": {
          "address": "8weM5kskjcg5A8SpfSkJGPVhL9RpJ7Lsu1Hs8ghSpump",
          "name": "Yummy ",
          "symbol": "CHOCOLATE"
        },
        "quoteToken": {
          "address": "So11111111111111111111111111111111111111112",
          "name": "Wrapped SOL",
          "symbol": "SOL"
        },
        "priceNative": "0.000001565",
        "priceUsd": "0.0001188",
        "txns": {
          "m5": {
            "buys": 1,
            "sells": 0
          },
          "h1": {
            "buys": 67,
            "sells": 42
          },
          "h6": {
            "buys": 577,
            "sells": 432
          },
          "h24": {
            "buys": 1065,
            "sells": 763
          }
        },
        "volume": {
          "h24": 128451.53,
          "h6": 68822.85,
          "h1": 4358.78,
          "m5": 24
        },
        "priceChange": {
          "m5": 0.25,
          "h1": 15.96,
          "h6": 58.41,
          "h24": 39.44
        },
        "liquidity": {
          "usd": 25671.29,
          "base": 108027182,
          "quote": 169.1465
        },
        "fdv": 118823,
        "marketCap": 118823,
        "pairCreatedAt": 1784116441000,
        "info": {
          "imageUrl": "https://cdn.dexscreener.com/cms/images/_bCVfSEE8T9F0cOI?width=800&height=800&quality=95&format=auto",
          "header": "https://cdn.dexscreener.com/cms/images/rIIh0QTA9G0vfm5L?width=1500&height=500&quality=95&format=auto",
          "openGraph": "https://cdn.dexscreener.com/token-images/og/solana/8weM5kskjcg5A8SpfSkJGPVhL9RpJ7Lsu1Hs8ghSpump?timestamp=1784234400000",
          "websites": [
            {
              "url": "https://www.yummychocolatesol.com/",
              "label": "Website"
            }
          ],
          "socials": [
            {
              "url": "https://x.com/yummychoco_sol",
              "type": "twitter"
            },
            {
              "url": "https://t.me/Yummychocolate_Sol",
              "type": "telegram"
            }
          ]
        },
        "boosts": {
          "active": 100
        }
      },
      "score": 1.591,
      "risk_score": 1,
      "risk_score_raw": 1,
      "risk_label": null,
      "risks_detail": [],
      "mint_authority_renounced": true,
      "freeze_authority_renounced": true,
      "lp_locked_pct": 100,
      "holder_count": 281,
      "top10_holder_pct": 55.8
    }
  ]
}